{
    "status": "OK", 
    "results": [
        {
            "geometry": {
                "location": {
                    "lat": -6.959192799999999, 
                    "lng": 107.707281
                }, 
                "viewport": {
                    "northeast": {
                        "lat": -6.957843819708497, 
                        "lng": 107.7086299802915
                    }, 
                    "southwest": {
                        "lat": -6.960541780291502, 
                        "lng": 107.7059320197085
                    }
                }, 
                "location_type": "ROOFTOP"
            }, 
            "address_components": [
                {
                    "long_name": "1", 
                    "types": [
                        "street_number"
                    ], 
                    "short_name": "1"
                }, 
                {
                    "long_name": "Jalan Utsman Bin Affan", 
                    "types": [
                        "route"
                    ], 
                    "short_name": "Jl. Utsman Bin Affan"
                }, 
                {
                    "long_name": "Rancanumpang", 
                    "types": [
                        "administrative_area_level_4", 
                        "political"
                    ], 
                    "short_name": "Rancanumpang"
                }, 
                {
                    "long_name": "Gedebage", 
                    "types": [
                        "administrative_area_level_3", 
                        "political"
                    ], 
                    "short_name": "Gedebage"
                }, 
                {
                    "long_name": "Kota Bandung", 
                    "types": [
                        "administrative_area_level_2", 
                        "political"
                    ], 
                    "short_name": "Kota Bandung"
                }, 
                {
                    "long_name": "Jawa Barat", 
                    "types": [
                        "administrative_area_level_1", 
                        "political"
                    ], 
                    "short_name": "Jawa Barat"
                }, 
                {
                    "long_name": "Indonesia", 
                    "types": [
                        "country", 
                        "political"
                    ], 
                    "short_name": "ID"
                }, 
                {
                    "long_name": "40295", 
                    "types": [
                        "postal_code"
                    ], 
                    "short_name": "40295"
                }
            ], 
            "place_id": "ChIJI-a9SvrCaC4RC4mfCp6SwSE", 
            "formatted_address": "Jl. Utsman Bin Affan No.1, Rancanumpang, Gedebage, Kota Bandung, Jawa Barat 40295, Indonesia", 
            "types": [
                "establishment", 
                "point_of_interest", 
                "school"
            ]
        }
    ]
}